{
    "0001": "leo visits the mental asylum to resolve his rice addiction",
    "0002": "Zhuowei eating onigiri at the condom convention",
    "0003": "Leo eating in an iHOP with his pancakes",
    "0004": "I like to eat my eggs raw",
    "0005": "We are eating good tonight!! Rice at IHOP!!!!!! SHEEESHHHH",
    "0006": "Kevin watching anime on Leo's iPad",
    "0007": "My sanity, 2023, colorized",
    "0008": "Flying to DC to spy on Aedan's sub convention",
    "0009": "Leo finding out there are 5 sides to a pentagon",
    "0010": "Wife: \"I wonder what he is thinking about\"",
    "0011": "Simple cheeseburger",
    "0012": "Aedan brings a gundam to Virginia",
    "0013": "Girl with robot body",
    "0014": "Leo's favorite waifu, male version",
    "0015": "Microscopic shark in the jungle",
    "0016": "I want to sleep now. why am i even here. please let me leave",
    "0017": "2023 Toyota Prius",
    "0018": "Leo going to the bar on a Saturday night",
    "0019": "Leo trying to fix the toilet for the 69420th time",
    "0020": "max buydakov drives his car into the ocean",
    "0021": "out of touch rich white girl in college",
    "0022": "I have a dream that one day this nation will rise up and li",
    "0023": "Leo sleeps like a little bitch",
    "0024": "Leo complains about all food except for rice",
    "0025": "leo sleeping after ditching his cse 120 group",
    "0026": "Leo gets lost in Ascent",
    "0027": "Church on Sunday",
    "0028": "Leo sucking Lincoln Monument's penis",
    "0029": "Aedan surfing on top of a firetruck",
    "0030": "Jeremiah eating a 6 inch sandwich with Leo watching hungrily",
    "0031": "I am a sheep but sigma male is I",
    "0032": "When Leo hears a school shooting but then realizes hes gay",
    "0033": "Leo punches Brian in his sleep at DC",
    "0034": "Kevin Builds a dog house out of dirt in minecraft",
    "0035": "IHOP AFTER BREAKFAST",
    "0036": "jeremiah works at a sperm bank in san diego"
}